p2p_framework/__init__.py
p2p_framework/decorator_types.py
p2p_framework/decorators.py
p2p_framework/event_queue.py
p2p_framework/networker.py
p2p_framework/py.typed
p2p_framework/service.py
p2p_framework/types.py
p2p_framework-0.2.0.dist-info/WHEEL
p2p_framework-0.2.0.dist-info/METADATA
p2p_framework-0.2.0.dist-info/RECORD
