Metadata-Version: 2.3
Name: p2p-framework
Version: 0.2.0
Summary: Add your description here
Author: ArcherHeffern
Author-email: ArcherHeffern <heffernarcher@gmail.com>
Requires-Dist: marshaller-library>=0.1.0
Requires-Python: >=3.14
